{ "Language":"English",
  "htmlLangAtt":"en",
  "h1": "Online video Converter",
  "h2": "Convert video for free online",
  "title": "Video Converter- Convert to video for free online",
  "TITLE":"Safevideokit - an online video editing kit",
  "meta": "Our online video converter tool is absolutely free and is easy to use. We make sure all your data is safe while you convert to video. We support a large range of audio formats like MP4, MKV, MOV etc.",
  "keywords":"key1,key2,key3,key4",
  "features": [
    {
      "name": "AVI to mov Converter",
      "description": "Convert AVI to MOV online",
      "color": "#ff615c",
      "icon": "/assets/star.svg",
      "url": "/convert-avi-to-mov"
    },
    {
      "name": "AVI to MP4 Converter",
      "description": "Convert AVI to MP4 online",
      "color": "#3867d6",
      "icon": "/assets/star.svg",
      "url": "/convert-avi-to-mp4"
    },
    {
      "name": "DVD to MP4 Converter",
      "description": "Convert DVD to MP4 online",
      "color": "#ff5e57",
      "icon": "/assets/star.svg",
      "url": "/convert-dvd-to-mp4"
    },
    {
      "name": "FLV to MP4 converter",
      "description": "Convert FLV to MP4 online",
      "color": "#4bcffa",
      "icon": "/assets/star.svg",
      "url": "/convert-flv-to-mp4"
    },
    {
      "name": "MKV to MOV converter",
      "description": "Convert MKV to MOV online",
      "color": "#0be881",
      "icon": "/assets/star.svg",
      "url": "/convert-mkv-to-mov"
    },
    {
      "name": "MKV to MP4 converter",
      "description": "Convert MKV to MP4 online",
      "color": "#c56cf0",
      "icon": "/assets/star.svg",
      "url": "/convert-mkv-to-mp4"
    },

    {
      "name": "MOV to AVI converter",
      "description": "Convert MOV to AVI online",
      "color": "#7d5fff",
      "icon": "/assets/star.svg",
      "url": "/convert-mov-to-avi"
    },
        {
      "name": "MOV to GIF file converter",
      "description": "Convert MOV to GIF online",
      "color": "#ffa502",
      "icon": "/assets/star.svg",
      "url": "/convert-mov-to-gif"
    },
    {
      "name": "MOV to MP4 converter",
      "description": "Convert MOV to MP4 online",
      "color": "#4cd137",
      "icon": "/assets/star.svg",
      "url": "/convert-mov-to-mp4"
    },
    {
      "name": "MOV to VMV conversion",
      "description": "Convert MOV to VMV online",
      "color": "#ff793f",
      "icon": "/assets/star.svg",
      "url": "/convert-mov-to-vmv"
    },
    {
      "name": "MP4 to AVI converter",
      "description": "Convert MP4 to AVI online",
      "color": "#9c88ff",
      "icon": "/assets/star.svg",
      "url": "/convert-mp4-to-avi"
    },
    {
      "name": "MP4 to DVD converter",
      "description": "Convert MP4 to DVD online",
      "color": "#ff615c",
      "icon": "/assets/star.svg",
      "url": "/convert-mp4-to-dvd"
    },
    {
      "name": "MP4 to GIF converter",
      "description": "Convert MP4 to GIF online",
      "color": "#33d9b2",
      "icon": "/assets/star.svg",
      "url": "/convert-mp4-to-gif"
    },
    {
      "name": "MP4 to MKV converter",
      "description": "Convert MP4 to MKV online",
      "color": "#e84118",
      "icon": "/assets/star.svg",
      "url": "/convert-mp4-to-mkv"
    },
    {
      "name": "MP4 to MOV converter",
      "description": "Convert MP4 to MKV online",
      "color": "#00a8ff",
      "icon": "/assets/star.svg",
      "url": "/convert-mp4-to-mov"
    },
    {
      "name": "MP4 to MPEG  converter",
      "description": "Convert MP4 to MPEG  online",
      "color": "#1dd1a1",
      "icon": "/assets/star.svg",
      "url": "/convert-mp4-to-mpeg"
    },
    {
      "name": "MP4 to video converter",
      "description": "Convert MP4 to video online",
      "color": "#18dcff",
      "icon": "/assets/star.svg",
      "url": "/convert-mp4-to-video"
    },
    {
      "name": "MPEG to MP4 converter",
      "description": "Convert MPEG to MP4 online",
      "color": "#5352ed",
      "icon": "/assets/star.svg",
      "url": "/convert-mpeg-to-mp4"
    },
    {
      "name": "Video to 3GP converter",
      "description": "Convert video to 3GP online",
      "color": "#ff7f50",
      "icon": "/assets/star.svg",
      "url": "/convert-video-to-3gp"
    },
    {
      "name": "Video to AVI converter",
      "description": "Convert video to AVI online",
      "color": "#2ed573",
      "icon": "/assets/star.svg",
      "url": "/convert-video-to-avi"
    },
    {
      "name": "Video to FLV converter",
      "description": "Convert Video to FLV online",
      "color": "#ff615c",
      "icon": "/assets/star.svg",
      "url": "/convert-video-to-flv"
    },
    {
      "name": "Video to GIF converter",
      "description": "Convert Video to GIF online",
      "color": "#706fd3",
      "icon": "/assets/star.svg",
      "url": "/convert-video-to-gif"
    },

    {
      "name": "Video to MP4 converter",
      "description": "Convert Video to MP4 online",
      "color": "#ff793f",
      "icon": "/assets/star.svg",
      "url": "/convert-video-to-mp4"
    },
    {
      "name": "WEBM to MP4 converter",
      "description": "Convert WEBM to MP4 online",
      "color": "#c56cf0",
      "icon": "/assets/star.svg",
      "url": "/convert-webm-to-mp4"
    }

  ]
  ,
  "StructuredDataWebsite": {
    "@type": "WebSite",
    "name": "appscms",
    "alternateName": "appscms",
    "url": "www.appscms.com"
  },
  "StructuredDataorganization": {
    "@type": "Organization",
    "url": "http://www.appscms.com",
    "logo": "http://www.example.com/images/logo.png" 
  }
}
